i2i/__init__.py
i2i/core.py
i2i/experimental_pymint.py
i2i/factories.py
i2i/pymint.py
i2i/util.py
i2i/examples/__init__.py
i2i/py2aiohttp/__init__.py
i2i/py2aiohttp/aiohttp_server_gen.py
i2i/py2cli/__init__.py
i2i/py2cli/scrap.py
i2i/py2json/__init__.py
i2i/py2json/obj2dict.py
i2i/py2openapi/__init__.py
i2i/py2openapi/openapi_gen.py
i2i/py2openapi/test.py
i2i/py2request/__init__.py
i2i/py2request/method_func_makers.py
i2i/py2request/py2request.py
i2i/tests/__init__.py
i2i/tests/test_pymint.py
i2i/tests/test_pymint_2.py
scrap/__init__.py
scrap/declarative_apis.py
scrap/scrap.py
i2i-0.0.1.dist-info/LICENSE
i2i-0.0.1.dist-info/METADATA
i2i-0.0.1.dist-info/WHEEL
i2i-0.0.1.dist-info/top_level.txt
i2i-0.0.1.dist-info/RECORD
